transformerkit/__init__.py
transformerkit/attention.py
transformerkit/components.py
transformerkit/config.py
transformerkit/decoder.py
transformerkit/encoder.py
transformerkit/model.py
transformerkit/utils.py
transformerkit/visualization.py
transformerkit-0.1.0.dist-info/licenses/LICENSE
transformerkit-0.1.0.dist-info/METADATA
transformerkit-0.1.0.dist-info/WHEEL
transformerkit-0.1.0.dist-info/top_level.txt
transformerkit-0.1.0.dist-info/RECORD
